pyln/proto/__init__.py
pyln/proto/bech32.py
pyln/proto/invoice.py
pyln/proto/message/Makefile
pyln/proto/message/__init__.py
pyln/proto/message/array_types.py
pyln/proto/message/fundamental_types.py
pyln/proto/message/message.py
pyln/proto/onion.py
pyln/proto/primitives.py
pyln/proto/wire.py
pyln/proto/zbase32.py
pyln_proto_macros-23.5.2.dist-info/METADATA
pyln_proto_macros-23.5.2.dist-info/WHEEL
pyln_proto_macros-23.5.2.dist-info/RECORD
