Metadata-Version: 2.1
Name: pyln-proto-macros
Version: 23.5.2
Summary: This package implements some of the Lightning Network protocol in pure python. It is intended for protocol testing and some minor tooling only. It is not deemed secure enough to handle any amount of real funds (you have been warned!).
License: BSD-MIT
Author: Christian Decker
Author-email: decker.christian@gmail.com
Requires-Python: >=3.7,<4.0
Classifier: License :: Other/Proprietary License
Classifier: Programming Language :: Python :: 3
Classifier: Programming Language :: Python :: 3.7
Classifier: Programming Language :: Python :: 3.8
Classifier: Programming Language :: Python :: 3.9
Classifier: Programming Language :: Python :: 3.10
Classifier: Programming Language :: Python :: 3.11
Requires-Dist: PySocks (>=1,<2)
Requires-Dist: base58 (>=2.1.1,<3.0.0)
Requires-Dist: bitstring (>=3,<4)
Requires-Dist: coincurve (>=18,<19)
Requires-Dist: cryptography (>=41,<42)
